[
    {
        "icon": "bx bx-note",
        "content": "xxxxx xxxxxxxxxx xxxxxxxxxx xxxxxxxx xxxx"
    },
    {
        "icon": "bx bx-receipt",
        "content": "xxxxx xxxxxxxxxx xxxxxxxxxx xxxxxxxx xxxx"
    },
    {
        "icon": "bx bx-note",
        "content": "xxxxx xxxxxxxxxx xxxxxxxxxx xxxxxxxx xxxx"
    },
    {
        "icon": "bx bx-receipt",
        "content": "xxxxx xxxxxxxxxx xxxxxxxxxx xxxxxxxx xxxx"
    },
    {
        "icon": "bx bx-note",
        "content": "xxxxx xxxxxxxxxx xxxxxxxxxx xxxxxxxx xxxx"
    }
]